GmMonitorix/CGI.py
GmMonitorix/__init__.py
GmMonitorix/__main__.py
GmMonitorix/fs.py
GmMonitorix/icecast.py
GmMonitorix/net.py
GmMonitorix/system.py
gmmonitorix-0.1.2.dist-info/licenses/COPYING
gmmonitorix-0.1.2.dist-info/METADATA
gmmonitorix-0.1.2.dist-info/WHEEL
gmmonitorix-0.1.2.dist-info/entry_points.txt
gmmonitorix-0.1.2.dist-info/top_level.txt
gmmonitorix-0.1.2.dist-info/RECORD
