Metadata-Version: 2.4
Name: GmMonitorix
Version: 0.1.2
Summary: Monitorix Frontend for Gemini Protocol
Author: Cthulhu Fhtagn
License-Expression: GPL-2.0-only
Project-URL: Homepage, https://codeberg.org/cthulhu/gm-monitorix-cgi
Project-URL: Issues, https://codeberg.org/cthulhu/gm-monitorix-cgi/issues
Classifier: Programming Language :: Python :: 3
Classifier: Operating System :: POSIX :: Linux
Requires-Python: >=3.8
License-File: COPYING
Requires-Dist: rrdtool
Requires-Dist: brasciichart>=0.2
Dynamic: license-file
